statispy/__init__.py
statispy/correlation.py
statispy/sample.py
statispy/statispyError.py
statispy/stats.py
statispy-1.0.0.dist-info/LICENSE
statispy-1.0.0.dist-info/METADATA
statispy-1.0.0.dist-info/WHEEL
statispy-1.0.0.dist-info/top_level.txt
statispy-1.0.0.dist-info/RECORD
